setup.py
wutang/__init__.py
wutang/wutang.py
wutang/wutang.yaml
wutang.egg-info/PKG-INFO
wutang.egg-info/SOURCES.txt
wutang.egg-info/dependency_links.txt
wutang.egg-info/entry_points.txt
wutang.egg-info/requires.txt
wutang.egg-info/top_level.txt