Metadata-Version: 1.1
Name: wutang
Version: 0.0.1
Summary: generate names. laugh about it.
Home-page: https://github.com/smlstvnh/wutang
Author: samstav
Author-email: smlstvnh@gmail.com
License: GNU GPL
Keywords: wutang
Platform: UNKNOWN
Classifier: Programming Language :: Python
